lilliepy_server_component/__init__.py
lilliepy_server_component/main.py
lilliepy_server_component-1.0.0.dist-info/METADATA
lilliepy_server_component-1.0.0.dist-info/WHEEL
lilliepy_server_component-1.0.0.dist-info/top_level.txt
lilliepy_server_component-1.0.0.dist-info/RECORD
