Metadata-Version: 2.1
Name: lilliepy server component
Version: 1.0.0
Summary: a function to run code on a server, away from the client
Home-page: https://github.com/websitedeb/lilliepy_server
Author: sarthak ghoshal
Author-email: sarthak22.ghoshal@gmail.com
License: MIT
Keywords: lilliepy server components,lilliepy,reactpy
Classifier: Development Status :: 5 - Production/Stable
Classifier: Intended Audience :: Developers
Classifier: License :: OSI Approved :: MIT License
Classifier: Programming Language :: Python :: 3
Classifier: Programming Language :: Python :: 3.8
Classifier: Programming Language :: Python :: 3.9
Classifier: Programming Language :: Python :: 3.10
Classifier: Programming Language :: Python :: 3.11
Classifier: Framework :: Flask
Requires-Python: >=3.8
Requires-Dist: Flask>=2.0.0
Requires-Dist: requests>=2.0.0
